pypacgen/DNSDomainIs.py
pypacgen/IsInNet.py
pypacgen/IsPlainHostName.py
pypacgen/MonthRange.py
pypacgen/PACBlock.py
pypacgen/PACExceptions.py
pypacgen/PACFile.py
pypacgen/PACFunction.py
pypacgen/PACObject.py
pypacgen/PACReturn.py
pypacgen/ShExpMatchHost.py
pypacgen/ShExpMatchUrl.py
pypacgen/TimeRange.py
pypacgen/WeekdayRange.py
pypacgen/__init__.py
pypacgen/util.py
tests/__init__.py
tests/test_pac_file.py
pypacgen-1.0.0.dist-info/LICENSE.txt
pypacgen-1.0.0.dist-info/METADATA
pypacgen-1.0.0.dist-info/WHEEL
pypacgen-1.0.0.dist-info/top_level.txt
pypacgen-1.0.0.dist-info/RECORD
