Metadata-Version: 2.1
Name: pypacgen
Version: 1.0.0
Summary: A module to generate Proxy Auto Config files on the fly.
Author: Kayleigh Conti
Author-email: kc8528@pm.me
License: MIT
Classifier: Programming Language :: Python :: 3
Classifier: License :: OSI Approved :: MIT License
Classifier: Operating System :: OS Independent
Requires-Python: >=3.10
License-File: LICENSE.txt
